README.txt
setup.py
collective/__init__.py
collective.randomheaderimage.egg-info/PKG-INFO
collective.randomheaderimage.egg-info/SOURCES.txt
collective.randomheaderimage.egg-info/dependency_links.txt
collective.randomheaderimage.egg-info/entry_points.txt
collective.randomheaderimage.egg-info/namespace_packages.txt
collective.randomheaderimage.egg-info/not-zip-safe
collective.randomheaderimage.egg-info/requires.txt
collective.randomheaderimage.egg-info/top_level.txt
collective/randomheaderimage/__init__.py
collective/randomheaderimage/configure.zcml
collective/randomheaderimage/profiles.zcml
collective/randomheaderimage/browser/__init__.py
collective/randomheaderimage/browser/configure.zcml
collective/randomheaderimage/browser/interfaces.py
collective/randomheaderimage/browser/portal_header.pt
collective/randomheaderimage/browser/random_image.py
collective/randomheaderimage/profiles/default/browserlayer.xml
collective/randomheaderimage/profiles/default/metadata.xml
collective/randomheaderimage/profiles/default/propertiestool.xml
docs/HISTORY.txt