Metadata-Version: 1.0
Name: collective.randomheaderimage
Version: 0.1.0
Summary: Provide a random header to display into the header
Home-page: http://svn.plone.org/svn/collective/collective.randomheaderimage/
Author: RedTurtle Technology
Author-email: sviluppoplone@redturtle.net
License: GPL
Platform: UNKNOWN
Classifier: Programming Language :: Python
Classifier: Framework :: Plone
Classifier: Framework :: Plone :: 4.0
Classifier: Framework :: Plone :: 4.1
